MANIFEST.in
setup.py
occam/__init__.py
occam/app.py
occam/data.py
occam/runtime.py
occam/util.py
occam/version.py
occam/views.py
occam.egg-info/PKG-INFO
occam.egg-info/SOURCES.txt
occam.egg-info/dependency_links.txt
occam.egg-info/requires.txt
occam.egg-info/top_level.txt
occam/background/__init__.py
occam/background/background_app.py
occam/background/collector.py
occam/static/favicon.ico
occam/static/css/bootstrap-3.1.1-theme.css
occam/static/css/bootstrap-3.1.1-theme.css.map
occam/static/css/bootstrap-3.1.1-theme.min.css
occam/static/css/bootstrap-3.1.1.css
occam/static/css/bootstrap-3.1.1.css.map
occam/static/css/bootstrap-3.1.1.min.css
occam/static/css/occam.css
occam/static/fonts/glyphicons-halflings-regular.eot
occam/static/fonts/glyphicons-halflings-regular.svg
occam/static/fonts/glyphicons-halflings-regular.ttf
occam/static/fonts/glyphicons-halflings-regular.woff
occam/static/js/angular-1.3.0-beta1.min.js
occam/static/js/bootstrap-3.1.1.js
occam/static/js/bootstrap-3.1.1.min.js
occam/static/js/jquery-2.0.3.min.js
occam/static/js/occam/activity_feed.js
occam/static/js/occam/collection.js
occam/templates/activity.html
occam/templates/activity_component.html
occam/templates/base.html
occam/templates/collection.html
occam/templates/collection_view.html
occam/templates/index.html
tests/__init__.py