Metadata-Version: 1.1
Name: occam
Version: 0.1.4
Summary: A web frontend for the Razor imaging server.
Home-page: https://github.com/fhats/occam
Author: Fred Hatfull
Author-email: fred.hatfull@gmail.com
License: MIT
Keywords: razor razor-server imaging web
Platform: UNKNOWN
Classifier: Development Status :: 3 - Alpha
Classifier: Topic :: Utilities
Classifier: License :: OSI Approved :: MIT License
Classifier: Topic :: Software Development :: Libraries
Classifier: Topic :: Software Development :: Libraries :: Python Modules
Classifier: Topic :: System :: Systems Administration
Classifier: Topic :: System :: Installation/Setup
